Workbook

Sheet Calculadora
B2: CUSTOS OPERACIONAIS — AÇÕES (XP Investimentos + B3)
B3: Preencha apenas as células AMARELAS. Todo o resto é calculado. As alíquotas ficam na aba 'Parâmetros'.
B5: 1. OPERAÇÃO
B6: Preço da ação (R$) | C6: 37.52 | F6: quanto custa 1 ação
B7: Quantidade (ações) | C7: 300 | F7: lote da B3 = múltiplo de 100
B8: Tipo de operação | C8: Day Trade | F8: Swing Trade ou Day Trade
B9: Operação vendida (aluguel BTC)? | C9: Não | F9: só 'Sim' se você VENDE ação que não tem
B10: Dias corridos carregados | C10: 1 | F10: usado só no aluguel; Day Trade ignora
B12: Financeiro da operação (R$) | C12: =C6*C7 -> 11256 | F12: preço × quantidade
B14: 2. CUSTO POR ORDEM EXECUTADA
C15: Alíquota | D15: Valor (R$)
B16: Corretagem | C16: =IF(C8="Day Trade",Parametros!C6,Parametros!C5) -> 2.9 | D16: =C16 -> 2.9 | F16: XP: R$ 4,90 swing | R$ 2,90 day (R$ 0 com RLP)
B17: Impostos sobre a corretagem | C17: =Parametros!C7 -> 0.0965 | D17: =D16*C17 -> 0.27985 | F17: ISS 5% + PIS 0,65% + COFINS 4%
B18: B3 — taxa de negociação | C18: =Parametros!C10 -> 5e-05 | D18: =$C$12*C18 -> 0.5628 | F18: emolumentos
B19: B3 — taxa de liquidação | C19: =IF(C8="Day Trade",Parametros!C12,Parametros!C11) -> 0.00018 | D19: =$C$12*C19 -> 2.02608 | F19: swing 0,0250% | day trade 0,0180%
B20: Taxa operacional XP | C20: =Parametros!C8 -> 0.059 | D20: =(D16+D18+D19)*C20 -> 0.32384392 | F20: 5,9% sobre corretagem + emolumentos + liquidação
B21: CUSTO DE 1 ORDEM | D21: =SUM(D16:D20) -> 6.0925739
B23: 3. ALUGUEL DE AÇÕES (BTC) — só na ponta vendida em Swing Trade
B24: Taxa fixa XP ao tomador | C24: =Parametros!C15 -> 0.0025 | D24: =IF(AND(C9="Sim",C8="Swing Trade"),$C$12*C24,0) -> 0 | F24: 0,25% sobre o volume — NÃO depende do prazo
B25: Taxa do Papel (% ao ano) | C25: =Parametros!C16 -> 0.02 | D25: =IF(AND(C9="Sim",C8="Swing Trade"),$C$12*C25*C10/Parametros!C17,0) -> 0 | F25: varia por papel e por dia — consulte no Home Broker
B26: CUSTO DE ALUGUEL | D26: =D24+D25 -> 0
B28: 4. CUSTO TOTAL DO GIRO (abrir + fechar)
B29: Custo das 2 ordens | D29: =D21*2 -> 12.185148 | F29: 1 para abrir, 1 para fechar
B30: Aluguel | D30: =D26 -> 0
B31: CUSTO TOTAL | D31: =D29+D30 -> 12.185148
B32: Custo em % do financeiro | D32: =IF($C$12=0,0,D31/$C$12) -> 0.0010825469 | F32: quanto o giro consome do capital alocado
B33: Custo por ação (R$) | D33: =IF(C7=0,0,D31/C7) -> 0.040617159 | F33: quanto a ação precisa andar só para empatar
B34: Variação necessária para empatar | D34: =IF(C6=0,0,D33/C6) -> 0.0010825469 | F34: em % do preço da ação
B36: 5. OPERAÇÃO DE DUAS PERNAS (Long & Short) — opcional
B37: Preencha a segunda perna abaixo. A perna 1 é a da seção 1. A perna vendida paga aluguel em Swing Trade.
B38: Perna 2 — preço da ação (R$) | C38: 15.73
B39: Perna 2 — quantidade (ações) | C39: 200
B40: Perna 2 é a vendida? | C40: Sim | F40: normalmente sim, se a perna 1 é comprada
B41: Financeiro da perna 2 | C41: =C38*C39 -> 3146
B42: Custo das 2 ordens da perna 2 | D42: =2*((IF(C8="Day Trade",Parametros!C6,Parametros!C5))*(1+Parametros!C7)+$C$41*(Parametros!C10+IF(C8="Day Trade",Parametros!C12,Parametros!C11))+((IF(C8="Day Trade",Parametros!C6,Parametros!C5))+$C$41*(Parametros!C10+IF(C8="Day Trade",Parametros!C12,Parametros!C11)))*Parametros!C8) -> 8.2344424 | F42: mesma estrutura de taxas
B43: Aluguel da perna 2 | D43: =IF(AND(C40="Sim",C8="Swing Trade"),$C$41*Parametros!C15+$C$41*Parametros!C16*C10/Parametros!C17,0) -> 0
B44: CUSTO TOTAL DAS DUAS PERNAS | D44: =D31+D42+D43 -> 20.41959
B45: Financeiro total alocado | D45: =$C$12+$C$41 -> 14402 | F45: soma das duas pernas
B46: Custo em % do financeiro total | D46: =IF(D45=0,0,D44/D45) -> 0.0014178302
B48: ATENÇÃO: se você usa robô/estratégia automatizada, confirme a corretagem com seu assessor. Para minicontratos a XP exclui explicitamente 'estratégias automatizadas' do benefício de corretagem zero; para ações o texto é ambíguo.

Sheet Parametros
B2: PARÂMETROS — edite aqui quando as tabelas mudarem
B3: Todas as células amarelas são editáveis. A Calculadora referencia esta aba.
B4: CORRETAGEM E TAXAS DA CORRETORA (XP)
B5: Corretagem por ordem — Swing Trade | C5: 4.9 | D5: XP, cliente assessorado pela XP / autoatendimento. Escritório credenciado: R$ 18,90
B6: Corretagem por ordem — Day Trade | C6: 2.9 | D6: XP, não aderindo ao RLP. Aderindo ao RLP: R$ 0,00
B7: Impostos sobre a corretagem | C7: 0.0965 | D7: ISS 5% + PIS 0,65% + COFINS 4%. Confirmar se já vêm embutidos na nota
B8: Taxa operacional XP | C8: 0.059 | D8: 5,9% sobre corretagem + emolumentos + taxa de liquidação
B9: TAXAS DA B3 (% sobre o financeiro, por ponta)
B10: Taxa de negociação (emolumentos) | C10: 5e-05 | D10: 0,0050% — varia com o volume médio mensal do investidor
B11: Taxa de liquidação — Swing Trade | C11: 0.00025 | D11: 0,0250%. Total swing = 0,0300%
B12: Taxa de liquidação — Day Trade | C12: 0.00018 | D12: 0,0180% até R$ 1 milhão/dia. Total day trade = 0,0230%
B14: ALUGUEL DE AÇÕES (BTC)
B15: Taxa fixa XP ao tomador | C15: 0.0025 | D15: 0,25% sobre o volume financeiro do aluguel. NÃO depende do prazo
B16: Taxa do Papel (% ao ano) | C16: 0.02 | D16: PLACEHOLDER — varia por papel e por dia. Consulte no Home Broker, menu BTC
B17: Dias úteis no ano | C17: 252 | D17: base para converter a taxa anual em diária
B19: FONTES
B20: • Corretagem, impostos e taxa operacional: xpi.com.br/custos-operacionais (consultado em 20/08/2026)
B21: • Taxas B3 mercado à vista de ações, pessoa física: tabela pública B3
B22: • Taxa do Papel do BTC: informada pelo cliente / Home Broker XP — o valor aqui é placeholder
B24: LEGENDA: células AMARELAS com texto AZUL são entradas editáveis. Texto preto é fórmula — não edite.
